ik_geo-1.0.3.dist-info/METADATA
ik_geo-1.0.3.dist-info/WHEEL
ik_geo-1.0.3.dist-info/license_files/LICENSE
ik_geo/ik_geo.pyi
ik_geo/__init__.py
ik_geo/py.typed
ik_geo/ik_geo.cpython-312-darwin.so
ik_geo-1.0.3.dist-info/RECORD
