Metadata-Version: 2.3
Name: ik-geo
Version: 1.0.3
Classifier: Programming Language :: Rust
Classifier: Programming Language :: Python :: Implementation :: CPython
Classifier: Programming Language :: Python :: Implementation :: PyPy
License-File: LICENSE
Summary: Analytic IK solver for 6 and 7 axes robot arms. Algorithm adapted from IK-Geo (https://arxiv.org/pdf/2211.05737)
Requires-Python: >=3.8
